JavaGui/__init__.py
JavaGui/_core.abi3.so
JavaGui/assertions/__init__.py
JavaGui/assertions/formatters.py
JavaGui/assertions/security.py
JavaGui/deprecation.py
JavaGui/jars/javagui-agent.jar
JavaGui/keywords/__init__.py
JavaGui/keywords/getters.py
JavaGui/keywords/rcp_keywords.py
JavaGui/keywords/swt_getters.py
JavaGui/keywords/swt_tables.py
JavaGui/keywords/swt_trees.py
JavaGui/keywords/tables.py
JavaGui/py.typed
robotframework_javagui-0.2.0.dist-info/METADATA
robotframework_javagui-0.2.0.dist-info/WHEEL
robotframework_javagui-0.2.0.dist-info/licenses/LICENSE
robotframework_javagui-0.2.0.dist-info/RECORD
