Metadata-Version: 2.4
Name: robotframework-javagui
Version: 0.2.0
Classifier: Development Status :: 4 - Beta
Classifier: Framework :: Robot Framework
Classifier: Framework :: Robot Framework :: Library
Classifier: Intended Audience :: Developers
Classifier: License :: OSI Approved :: Apache Software License
Classifier: Operating System :: OS Independent
Classifier: Programming Language :: Python :: 3
Classifier: Programming Language :: Python :: 3.8
Classifier: Programming Language :: Python :: 3.9
Classifier: Programming Language :: Python :: 3.10
Classifier: Programming Language :: Python :: 3.11
Classifier: Programming Language :: Python :: 3.12
Classifier: Programming Language :: Rust
Classifier: Topic :: Software Development :: Testing
Classifier: Topic :: Software Development :: Quality Assurance
Requires-Dist: docutils>=0.20.1
Requires-Dist: robotframework>=4.0
Requires-Dist: robotframework-assertion-engine>=3.0.0
Requires-Dist: pytest>=7.0 ; extra == 'dev'
Requires-Dist: pytest-cov>=4.0 ; extra == 'dev'
Requires-Dist: black>=23.0 ; extra == 'dev'
Requires-Dist: mypy>=1.0 ; extra == 'dev'
Requires-Dist: ruff>=0.1 ; extra == 'dev'
Provides-Extra: dev
License-File: LICENSE
Summary: High-performance Robot Framework library for Java GUI automation (Swing, SWT, Eclipse RCP)
Keywords: robotframework,swing,swt,rcp,eclipse,java,automation,testing,gui
Author: robotframework-javagui contributors
License: Apache-2.0
Requires-Python: >=3.8.1
Project-URL: Documentation, https://robotframework-javagui.readthedocs.io
Project-URL: Homepage, https://github.com/robotframework/robotframework-javagui
Project-URL: Issues, https://github.com/robotframework/robotframework-javagui/issues
Project-URL: Repository, https://github.com/robotframework/robotframework-javagui
